booru/__init__.py
booru/admin.py
booru/apps.py
booru/context_processors.py
booru/forms.py
booru/managers.py
booru/models.py
booru/sitemaps.py
booru/urls.py
booru/utils.py
booru/views.py
booru/account/__init__.py
booru/account/admin.py
booru/account/apps.py
booru/account/decorators.py
booru/account/forms.py
booru/account/models.py
booru/account/tests.py
booru/account/urls.py
booru/account/views.py
booru/account/migrations/0001_initial.py
booru/account/migrations/0002_auto_20181113_2121.py
booru/account/migrations/0003_auto_20181113_2139.py
booru/account/migrations/0004_auto_20181130_1530.py
booru/account/migrations/0005_alter_account_first_name.py
booru/account/migrations/0006_alter_account_id_alter_privilege_id_alter_timeout_id.py
booru/account/migrations/__init__.py
booru/account/static/booru/account/js/profile.js
booru/core/__init__.py
booru/core/admin.py
booru/core/apps.py
booru/core/forms.py
booru/core/models.py
booru/core/tests.py
booru/core/urls.py
booru/core/views.py
booru/core/migrations/0001_initial.py
booru/core/migrations/0002_bannedhash.py
booru/core/migrations/0003_auto_20181120_1549.py
booru/core/migrations/0004_auto_20181120_1657.py
booru/core/migrations/0005_auto_20181120_1943.py
booru/core/migrations/0006_postflag.py
booru/core/migrations/0007_postflag_status.py
booru/core/migrations/0008_auto_20181209_2237.py
booru/core/migrations/0009_auto_20181210_2031.py
booru/core/migrations/0010_alter_bannedhash_id_alter_postflag_id.py
booru/core/migrations/__init__.py
booru/migrations/0001_initial.py
booru/migrations/0002_auto_20181113_2136.py
booru/migrations/0003_auto_20181118_1918.py
booru/migrations/0004_auto_20181118_2126.py
booru/migrations/0005_auto_20181206_1852.py
booru/migrations/0006_comment_is_hidden.py
booru/migrations/0007_auto_20181211_2031.py
booru/migrations/0008_auto_20181213_1831.py
booru/migrations/0009_alter_historicalgallery_options_and_more.py
booru/migrations/0010_alter_category_id_alter_comment_id_and_more.py
Boorunaut-0.5.0.dist-info/LICENSE
Boorunaut-0.5.0.dist-info/METADATA
Boorunaut-0.5.0.dist-info/WHEEL
Boorunaut-0.5.0.dist-info/entry_points.txt
Boorunaut-0.5.0.dist-info/top_level.txt
Boorunaut-0.5.0.dist-info/RECORD
