Metadata-Version: 2.1
Name: Boorunaut
Version: 0.5.0
Summary: A taggable imageboard built in Django.
Home-page: https://github.com/Boorunaut/Boorunaut
Author: LucasCTN, ThiagoCamposTN
Author-email: lucascampostn@gmail.com, thiagocampostn@gmail.com
License: MIT License
Platform: UNKNOWN
Classifier: Environment :: Web Environment
Classifier: Framework :: Django
Classifier: Intended Audience :: Developers
Classifier: License :: OSI Approved :: MIT License
Classifier: Operating System :: OS Independent
Classifier: Programming Language :: Python
Classifier: Programming Language :: Python :: 3.5
Classifier: Programming Language :: Python :: 3.6
Classifier: Topic :: Internet :: WWW/HTTP
Classifier: Topic :: Internet :: WWW/HTTP :: Dynamic Content
License-File: LICENSE
Requires-Dist: Django (==5.0.4)
Requires-Dist: Pillow (==10.3.0)
Requires-Dist: diff-match-patch (==20200713)
Requires-Dist: django-cors-headers (==4.3.0)
Requires-Dist: django-crispy-forms (==1.14.0)
Requires-Dist: django-markdownify (==0.9.2)
Requires-Dist: django-ninja-jwt (==5.2.6)
Requires-Dist: django-role-permissions (==3.1.1)
Requires-Dist: django-simple-history (==3.2.0)
Requires-Dist: django-taggit (==5.0.1)
Requires-Dist: ffmpeg-python (==0.2.0)
Requires-Dist: markdown2 (==2.4.7)
Requires-Dist: olefile (==0.46)
Requires-Dist: orjson (==3.9.9)
Requires-Dist: pytz (==2022.7.1)
Requires-Dist: requests (==2.31.0)
Requires-Dist: six (==1.16.0)
